gateway/__init__.py
gateway/alembic.ini
gateway/migrations/README
gateway/migrations/__init__.py
gateway/migrations/env.py
gateway/migrations/script.py.mako
gateway/migrations/versions/89c0b1e53a97_make_group_unique.py
gateway/migrations/versions/__init__.py
gateway/migrations/versions/b34c224cb930_response_model.py
gateway/migrations/versions/cf23041fc89b_add_method.py
gateway/migrations/versions/d1152876f1d9_params.py
gateway/migrations/versions/dd39ade2f2df_override_headers.py
gateway/migrations/versions/e2b4bedc6444_initial.py
gateway/server/__init__.py
gateway/server/core/__init__.py
gateway/server/core/config.py
gateway/server/core/database/__init__.py
gateway/server/core/database/crud.py
gateway/server/core/database/models.py
gateway/server/core/database/schemas.py
gateway/server/core/decorators.py
gateway/server/core/management/__init__.py
gateway/server/core/management/migrate.py
gateway/server/core/request.py
gateway/server/core/router.py
gateway/server/routes.py
gateway/server/utils/__init__.py
gateway/server/utils/body.py
gateway/server/utils/form.py
gateway/server/utils/headers.py
gateway/server/utils/query.py
gateway/server/utils/request.py
gateway/server/utils/response.py
gateway/server/utils/router.py
mini_fastapi_gateway-0.0.2b10.dist-info/LICENSE
mini_fastapi_gateway-0.0.2b10.dist-info/METADATA
mini_fastapi_gateway-0.0.2b10.dist-info/WHEEL
mini_fastapi_gateway-0.0.2b10.dist-info/entry_points.txt
mini_fastapi_gateway-0.0.2b10.dist-info/RECORD
