Metadata-Version: 2.1
Name: mini-fastapi-gateway
Version: 0.0.2b10
Summary: 
Author: aizhigito
Author-email: 82809523+aizhigito@users.noreply.github.com
Requires-Python: >=3.11,<4.0
Classifier: Programming Language :: Python :: 3
Classifier: Programming Language :: Python :: 3.11
Requires-Dist: aiohttp (>=3.8.5,<4.0.0)
Requires-Dist: alembic (>=1.12.0,<2.0.0)
Requires-Dist: cachetools (>=5.3.1,<6.0.0)
Requires-Dist: fastapi (>=0.103.2,<0.104.0)
Requires-Dist: pydantic-settings (>=2.0.3,<3.0.0)
Requires-Dist: sqlalchemy (>=2.0.21,<3.0.0)
Requires-Dist: ujson (>=5.8.0,<6.0.0)
